<?xml version="1.0" ?>
<Gesture Name="right_sq_bracket08" Subject="01" Number="08" NumPts="195">
	<Point X="147" Y="198" T="0"/>
	<Point X="148" Y="198" T="1"/>
	<Point X="149" Y="198" T="2"/>
	<Point X="150" Y="198" T="3"/>
	<Point X="151" Y="198" T="4"/>
	<Point X="152" Y="198" T="5"/>
	<Point X="153" Y="198" T="6"/>
	<Point X="154" Y="198" T="7"/>
	<Point X="155" Y="198" T="8"/>
	<Point X="156" Y="198" T="9"/>
	<Point X="157" Y="198" T="10"/>
	<Point X="158" Y="198" T="11"/>
	<Point X="159" Y="198" T="12"/>
	<Point X="160" Y="198" T="13"/>
	<Point X="161" Y="198" T="14"/>
	<Point X="162" Y="198" T="15"/>
	<Point X="163" Y="198" T="16"/>
	<Point X="164" Y="198" T="17"/>
	<Point X="165" Y="198" T="18"/>
	<Point X="165" Y="199" T="19"/>
	<Point X="166" Y="199" T="20"/>
	<Point X="167" Y="199" T="21"/>
	<Point X="168" Y="199" T="22"/>
	<Point X="169" Y="199" T="23"/>
	<Point X="170" Y="199" T="24"/>
	<Point X="171" Y="199" T="25"/>
	<Point X="172" Y="199" T="26"/>
	<Point X="173" Y="199" T="27"/>
	<Point X="174" Y="199" T="28"/>
	<Point X="175" Y="199" T="29"/>
	<Point X="176" Y="199" T="30"/>
	<Point X="177" Y="199" T="31"/>
	<Point X="178" Y="199" T="32"/>
	<Point X="179" Y="199" T="33"/>
	<Point X="180" Y="199" T="34"/>
	<Point X="181" Y="199" T="35"/>
	<Point X="182" Y="199" T="36"/>
	<Point X="182" Y="200" T="37"/>
	<Point X="182" Y="201" T="38"/>
	<Point X="182" Y="202" T="39"/>
	<Point X="183" Y="203" T="40"/>
	<Point X="183" Y="204" T="41"/>
	<Point X="183" Y="205" T="42"/>
	<Point X="183" Y="206" T="43"/>
	<Point X="183" Y="207" T="44"/>
	<Point X="183" Y="208" T="45"/>
	<Point X="184" Y="208" T="46"/>
	<Point X="184" Y="209" T="47"/>
	<Point X="184" Y="210" T="48"/>
	<Point X="184" Y="211" T="49"/>
	<Point X="184" Y="212" T="50"/>
	<Point X="184" Y="213" T="51"/>
	<Point X="184" Y="214" T="52"/>
	<Point X="184" Y="215" T="53"/>
	<Point X="184" Y="216" T="54"/>
	<Point X="184" Y="217" T="55"/>
	<Point X="184" Y="218" T="56"/>
	<Point X="185" Y="218" T="57"/>
	<Point X="185" Y="219" T="58"/>
	<Point X="185" Y="220" T="59"/>
	<Point X="185" Y="221" T="60"/>
	<Point X="185" Y="222" T="61"/>
	<Point X="185" Y="223" T="62"/>
	<Point X="185" Y="224" T="63"/>
	<Point X="185" Y="225" T="64"/>
	<Point X="185" Y="226" T="65"/>
	<Point X="185" Y="227" T="66"/>
	<Point X="185" Y="228" T="67"/>
	<Point X="186" Y="229" T="68"/>
	<Point X="186" Y="230" T="69"/>
	<Point X="186" Y="231" T="70"/>
	<Point X="186" Y="232" T="71"/>
	<Point X="186" Y="233" T="72"/>
	<Point X="186" Y="234" T="73"/>
	<Point X="186" Y="235" T="74"/>
	<Point X="186" Y="236" T="75"/>
	<Point X="186" Y="237" T="76"/>
	<Point X="186" Y="238" T="77"/>
	<Point X="186" Y="239" T="78"/>
	<Point X="186" Y="240" T="79"/>
	<Point X="186" Y="241" T="80"/>
	<Point X="186" Y="242" T="81"/>
	<Point X="186" Y="243" T="82"/>
	<Point X="186" Y="244" T="83"/>
	<Point X="186" Y="245" T="84"/>
	<Point X="186" Y="246" T="85"/>
	<Point X="186" Y="247" T="86"/>
	<Point X="186" Y="248" T="87"/>
	<Point X="186" Y="249" T="88"/>
	<Point X="186" Y="250" T="89"/>
	<Point X="187" Y="250" T="90"/>
	<Point X="187" Y="251" T="91"/>
	<Point X="187" Y="252" T="92"/>
	<Point X="187" Y="253" T="93"/>
	<Point X="187" Y="254" T="94"/>
	<Point X="187" Y="255" T="95"/>
	<Point X="187" Y="257" T="96"/>
	<Point X="187" Y="259" T="97"/>
	<Point X="187" Y="260" T="98"/>
	<Point X="187" Y="261" T="99"/>
	<Point X="187" Y="262" T="100"/>
	<Point X="187" Y="263" T="101"/>
	<Point X="187" Y="264" T="102"/>
	<Point X="187" Y="265" T="103"/>
	<Point X="187" Y="266" T="104"/>
	<Point X="187" Y="267" T="105"/>
	<Point X="187" Y="268" T="106"/>
	<Point X="187" Y="269" T="107"/>
	<Point X="187" Y="270" T="108"/>
	<Point X="187" Y="271" T="109"/>
	<Point X="187" Y="272" T="110"/>
	<Point X="187" Y="273" T="111"/>
	<Point X="187" Y="274" T="112"/>
	<Point X="187" Y="275" T="113"/>
	<Point X="187" Y="276" T="114"/>
	<Point X="187" Y="277" T="115"/>
	<Point X="187" Y="278" T="116"/>
	<Point X="187" Y="279" T="117"/>
	<Point X="187" Y="280" T="118"/>
	<Point X="187" Y="281" T="119"/>
	<Point X="187" Y="282" T="120"/>
	<Point X="187" Y="283" T="121"/>
	<Point X="187" Y="284" T="122"/>
	<Point X="187" Y="285" T="123"/>
	<Point X="187" Y="286" T="124"/>
	<Point X="187" Y="287" T="125"/>
	<Point X="187" Y="288" T="126"/>
	<Point X="187" Y="289" T="127"/>
	<Point X="187" Y="290" T="128"/>
	<Point X="187" Y="291" T="129"/>
	<Point X="187" Y="292" T="130"/>
	<Point X="187" Y="293" T="131"/>
	<Point X="187" Y="294" T="132"/>
	<Point X="187" Y="295" T="133"/>
	<Point X="187" Y="296" T="134"/>
	<Point X="187" Y="297" T="135"/>
	<Point X="187" Y="298" T="136"/>
	<Point X="187" Y="299" T="137"/>
	<Point X="187" Y="300" T="138"/>
	<Point X="186" Y="300" T="139"/>
	<Point X="186" Y="301" T="140"/>
	<Point X="186" Y="302" T="141"/>
	<Point X="186" Y="303" T="142"/>
	<Point X="186" Y="304" T="143"/>
	<Point X="186" Y="305" T="144"/>
	<Point X="186" Y="306" T="145"/>
	<Point X="186" Y="307" T="146"/>
	<Point X="186" Y="308" T="147"/>
	<Point X="186" Y="309" T="148"/>
	<Point X="186" Y="310" T="149"/>
	<Point X="185" Y="310" T="150"/>
	<Point X="185" Y="311" T="151"/>
	<Point X="185" Y="312" T="152"/>
	<Point X="185" Y="313" T="153"/>
	<Point X="184" Y="313" T="154"/>
	<Point X="183" Y="313" T="155"/>
	<Point X="183" Y="314" T="156"/>
	<Point X="182" Y="314" T="157"/>
	<Point X="181" Y="314" T="158"/>
	<Point X="180" Y="314" T="159"/>
	<Point X="179" Y="314" T="160"/>
	<Point X="178" Y="314" T="161"/>
	<Point X="177" Y="314" T="162"/>
	<Point X="176" Y="314" T="163"/>
	<Point X="175" Y="314" T="164"/>
	<Point X="174" Y="314" T="165"/>
	<Point X="173" Y="314" T="166"/>
	<Point X="172" Y="314" T="167"/>
	<Point X="171" Y="314" T="168"/>
	<Point X="170" Y="314" T="169"/>
	<Point X="169" Y="314" T="170"/>
	<Point X="168" Y="314" T="171"/>
	<Point X="167" Y="314" T="172"/>
	<Point X="166" Y="313" T="173"/>
	<Point X="165" Y="313" T="174"/>
	<Point X="164" Y="313" T="175"/>
	<Point X="163" Y="313" T="176"/>
	<Point X="162" Y="313" T="177"/>
	<Point X="161" Y="313" T="178"/>
	<Point X="160" Y="313" T="179"/>
	<Point X="159" Y="313" T="180"/>
	<Point X="158" Y="313" T="181"/>
	<Point X="157" Y="313" T="182"/>
	<Point X="156" Y="313" T="183"/>
	<Point X="155" Y="313" T="184"/>
	<Point X="154" Y="313" T="185"/>
	<Point X="153" Y="313" T="186"/>
	<Point X="152" Y="313" T="187"/>
	<Point X="151" Y="313" T="188"/>
	<Point X="150" Y="313" T="189"/>
	<Point X="149" Y="313" T="190"/>
	<Point X="148" Y="313" T="191"/>
	<Point X="148" Y="312" T="192"/>
	<Point X="147" Y="312" T="193"/>
	<Point X="146" Y="312" T="194"/>
</Gesture>
