<?xml version="1.0" ?>
<Gesture Name="delete_mark10" Subject="05" Number="10" NumPts="137">
	<Point X="117" Y="135" T="0"/>
	<Point X="118" Y="135" T="1"/>
	<Point X="118" Y="136" T="2"/>
	<Point X="119" Y="136" T="3"/>
	<Point X="119" Y="137" T="4"/>
	<Point X="120" Y="139" T="5"/>
	<Point X="121" Y="140" T="6"/>
	<Point X="121" Y="141" T="7"/>
	<Point X="122" Y="142" T="8"/>
	<Point X="123" Y="144" T="9"/>
	<Point X="127" Y="149" T="10"/>
	<Point X="132" Y="154" T="11"/>
	<Point X="134" Y="157" T="12"/>
	<Point X="137" Y="161" T="13"/>
	<Point X="142" Y="167" T="14"/>
	<Point X="144" Y="169" T="15"/>
	<Point X="146" Y="172" T="16"/>
	<Point X="148" Y="174" T="17"/>
	<Point X="155" Y="183" T="18"/>
	<Point X="164" Y="194" T="19"/>
	<Point X="169" Y="200" T="20"/>
	<Point X="174" Y="207" T="21"/>
	<Point X="179" Y="213" T="22"/>
	<Point X="186" Y="221" T="23"/>
	<Point X="191" Y="227" T="24"/>
	<Point X="196" Y="233" T="25"/>
	<Point X="197" Y="234" T="26"/>
	<Point X="201" Y="239" T="27"/>
	<Point X="206" Y="245" T="28"/>
	<Point X="212" Y="253" T="29"/>
	<Point X="217" Y="258" T="30"/>
	<Point X="219" Y="262" T="31"/>
	<Point X="220" Y="263" T="32"/>
	<Point X="224" Y="267" T="33"/>
	<Point X="225" Y="268" T="34"/>
	<Point X="232" Y="275" T="35"/>
	<Point X="236" Y="279" T="36"/>
	<Point X="238" Y="282" T="37"/>
	<Point X="239" Y="283" T="38"/>
	<Point X="240" Y="284" T="39"/>
	<Point X="240" Y="285" T="40"/>
	<Point X="244" Y="289" T="41"/>
	<Point X="245" Y="291" T="42"/>
	<Point X="246" Y="291" T="43"/>
	<Point X="247" Y="292" T="44"/>
	<Point X="247" Y="293" T="45"/>
	<Point X="246" Y="293" T="46"/>
	<Point X="245" Y="293" T="47"/>
	<Point X="244" Y="293" T="48"/>
	<Point X="243" Y="293" T="49"/>
	<Point X="242" Y="293" T="50"/>
	<Point X="240" Y="293" T="51"/>
	<Point X="237" Y="293" T="52"/>
	<Point X="234" Y="293" T="53"/>
	<Point X="224" Y="293" T="54"/>
	<Point X="217" Y="293" T="55"/>
	<Point X="208" Y="293" T="56"/>
	<Point X="197" Y="293" T="57"/>
	<Point X="190" Y="293" T="58"/>
	<Point X="186" Y="293" T="59"/>
	<Point X="182" Y="294" T="60"/>
	<Point X="180" Y="294" T="61"/>
	<Point X="174" Y="294" T="62"/>
	<Point X="170" Y="294" T="63"/>
	<Point X="157" Y="296" T="64"/>
	<Point X="144" Y="296" T="65"/>
	<Point X="136" Y="297" T="66"/>
	<Point X="134" Y="297" T="67"/>
	<Point X="131" Y="297" T="68"/>
	<Point X="127" Y="297" T="69"/>
	<Point X="125" Y="297" T="70"/>
	<Point X="112" Y="297" T="71"/>
	<Point X="104" Y="297" T="72"/>
	<Point X="100" Y="297" T="73"/>
	<Point X="97" Y="297" T="74"/>
	<Point X="95" Y="297" T="75"/>
	<Point X="93" Y="296" T="76"/>
	<Point X="90" Y="296" T="77"/>
	<Point X="85" Y="295" T="78"/>
	<Point X="83" Y="295" T="79"/>
	<Point X="82" Y="294" T="80"/>
	<Point X="81" Y="294" T="81"/>
	<Point X="80" Y="294" T="82"/>
	<Point X="79" Y="294" T="83"/>
	<Point X="78" Y="293" T="84"/>
	<Point X="78" Y="292" T="85"/>
	<Point X="78" Y="291" T="86"/>
	<Point X="79" Y="291" T="87"/>
	<Point X="79" Y="290" T="88"/>
	<Point X="79" Y="289" T="89"/>
	<Point X="80" Y="288" T="90"/>
	<Point X="80" Y="287" T="91"/>
	<Point X="81" Y="286" T="92"/>
	<Point X="82" Y="283" T="93"/>
	<Point X="83" Y="280" T="94"/>
	<Point X="84" Y="278" T="95"/>
	<Point X="88" Y="274" T="96"/>
	<Point X="91" Y="269" T="97"/>
	<Point X="94" Y="265" T="98"/>
	<Point X="96" Y="263" T="99"/>
	<Point X="99" Y="259" T="100"/>
	<Point X="104" Y="253" T="101"/>
	<Point X="109" Y="246" T="102"/>
	<Point X="112" Y="242" T="103"/>
	<Point X="114" Y="239" T="104"/>
	<Point X="115" Y="238" T="105"/>
	<Point X="122" Y="229" T="106"/>
	<Point X="127" Y="222" T="107"/>
	<Point X="131" Y="217" T="108"/>
	<Point X="133" Y="213" T="109"/>
	<Point X="134" Y="212" T="110"/>
	<Point X="137" Y="207" T="111"/>
	<Point X="139" Y="206" T="112"/>
	<Point X="141" Y="203" T="113"/>
	<Point X="143" Y="199" T="114"/>
	<Point X="146" Y="196" T="115"/>
	<Point X="148" Y="192" T="116"/>
	<Point X="149" Y="191" T="117"/>
	<Point X="152" Y="187" T="118"/>
	<Point X="161" Y="175" T="119"/>
	<Point X="170" Y="163" T="120"/>
	<Point X="177" Y="155" T="121"/>
	<Point X="178" Y="154" T="122"/>
	<Point X="180" Y="151" T="123"/>
	<Point X="182" Y="149" T="124"/>
	<Point X="183" Y="148" T="125"/>
	<Point X="187" Y="143" T="126"/>
	<Point X="189" Y="140" T="127"/>
	<Point X="192" Y="137" T="128"/>
	<Point X="193" Y="136" T="129"/>
	<Point X="193" Y="135" T="130"/>
	<Point X="194" Y="134" T="131"/>
	<Point X="195" Y="132" T="132"/>
	<Point X="196" Y="131" T="133"/>
	<Point X="196" Y="130" T="134"/>
	<Point X="197" Y="129" T="135"/>
	<Point X="198" Y="129" T="136"/>
</Gesture>
